[1,["ad2j1PEVFBXI4rFeBZd00B","af3LHRjMdERK5QLPPFCI6d","cfv5MJkk1HkLew8XAXrKsQ@6c48a"],["node","root","data","_dragonAsset","_dragonAtlasAsset","_texture"],[["cc.Node",["_name","_components","_prefab","_children","_lscale","_parent"],2,9,4,2,5,1],["cc.UITransform",["node","__prefab","_contentSize"],3,1,4,5],["cc.Prefab",["_name"],2],["cc.CompPrefabInfo",["fileId"],2],["a97bbP1jrpAOKueZ/Uiwdhb",["IdleAnim","PlantUpper","RandomAnim","node","__prefab"],0,1,4],["cc.PrefabInfo",["fileId","instance","targetOverrides","nestedPrefabInstanceRoots","root","asset"],-1,1,1],["dragonBones.ArmatureDisplay",["playTimes","_defaultArmatureIndexValue","_armatureName","node","__prefab","_dragonAsset","_dragonAtlasAsset"],0,1,4,6,6],["dragonBones.DragonBonesAsset",["_name","_dragonBonesJson"],1],["dragonBones.DragonBonesAtlasAsset",["_name","_atlasJson","_atlasJsonData"],0]],[[3,0,2],[5,0,1,2,3,4,5,5],[2,0,2],[0,0,3,1,2,4,2],[0,0,5,1,2,2],[1,0,1,1],[1,0,1,2,1],[4,0,1,2,3,4,4],[6,0,1,2,3,4,5,6,4],[7,0,1,3],[8,0,1,2,4]],[[[[2,"ExplodeONutDIS"],[3,"ExplodeONutDIS",[-4],[[5,-2,[0,"23sJHyNwJLYoEdEyukwWPG"]],[7,"Idle1",null,["Rand11"],-3,[0,"fbfhcSMppAFoWPyzBguoBt"]]],[1,"c46/YsCPVOJYA4mWEpNYRx",null,null,null,-1,0],[1,0.5,0.5,1]],[4,"Body",1,[[6,-5,[0,"5dKfFUK1pKDrC/ri/lvds4"],[5,168,161.07]],[8,1,0,"ExplodeONut",-6,[0,"94w1JNm09CTL7Rpo8V4GF1"],0,1]],[1,"7drz/c+2RGVb79VQTJyYiF",null,null,null,1,0]]],0,[0,1,1,0,0,1,0,0,1,0,-1,2,0,0,2,0,0,2,0,2,1,6],[0,0],[3,4],[0,1]],[[[9,"PlantAnimate_ske","{\"frameRate\":30,\"name\":\"PlantAnimate\",\"version\":\"5.5\",\"compatibleVersion\":\"5.5\",\"armature\":[{\"type\":\"Armature\",\"frameRate\":30,\"name\":\"ExplodeONut\",\"aabb\":{\"x\":-80.53,\"y\":-138.64,\"width\":148.53,\"height\":161.07},\"bone\":[{\"name\":\"root\"},{\"length\":146,\"name\":\"main\",\"parent\":\"root\",\"transform\":{\"x\":4.2,\"y\":14.2815,\"skX\":-90.7235,\"skY\":-90.7235}},{\"name\":\"back\",\"parent\":\"main\",\"transform\":{\"x\":68.3976,\"y\":-3.3366,\"skX\":90.7235,\"skY\":90.7235}},{\"name\":\"facial\",\"parent\":\"main\",\"transform\":{\"x\":91.4126,\"y\":5.4956,\"skX\":90.7235,\"skY\":90.7235}},{\"name\":\"mid\",\"parent\":\"main\",\"transform\":{\"x\":144.2157,\"y\":-28.6052,\"skX\":90.7235,\"skY\":90.7235}},{\"name\":\"food_lightnings\",\"parent\":\"main\",\"transform\":{\"x\":71.873,\"y\":-3.4999,\"scX\":0.6247,\"scY\":0.6247}},{\"name\":\"armor\",\"parent\":\"main\",\"transform\":{\"x\":88.6491,\"y\":0.7768,\"skX\":90,\"skY\":90}},{\"length\":14,\"name\":\"eyebrowL\",\"parent\":\"facial\",\"transform\":{\"x\":-25.7409,\"y\":-30.1344,\"skX\":17.9389,\"skY\":17.9389}},{\"name\":\"mouth\",\"parent\":\"facial\",\"transform\":{\"x\":0.0048,\"y\":17.02}},{\"name\":\"eyeR\",\"parent\":\"facial\",\"transform\":{\"x\":22.3987,\"y\":-6.562,\"skX\":-6,\"skY\":-6,\"scX\":0.7656,\"scY\":0.8}},{\"name\":\"eyeL\",\"parent\":\"facial\",\"transform\":{\"x\":-23.3156,\"y\":-3.5144}},{\"length\":11,\"name\":\"eyebrowR\",\"parent\":\"facial\",\"transform\":{\"x\":18.7043,\"y\":-29.683,\"skX\":168.7399,\"skY\":168.7399}},{\"inheritScale\":false,\"name\":\"food_lightning\",\"parent\":\"food_lightnings\",\"transform\":{\"x\":42.8302,\"y\":59.187}},{\"inheritScale\":false,\"name\":\"food_lightning1\",\"parent\":\"food_lightnings\",\"transform\":{\"x\":-23.6204,\"y\":-20.2539}},{\"name\":\"armors\",\"parent\":\"armor\",\"transform\":{\"x\":-7.7307,\"y\":20.4709}},{\"name\":\"eyeHeartR\",\"parent\":\"eyeR\",\"transform\":{\"x\":-10.7202,\"y\":-0.2591,\"skX\":6,\"skY\":6,\"scX\":1.25,\"scY\":1.25}},{\"name\":\"eyeHeartL\",\"parent\":\"eyeL\",\"transform\":{\"x\":5.23,\"y\":0.367}},{\"length\":8,\"name\":\"eyeCover\",\"parent\":\"eyeR\",\"transform\":{\"x\":1.0848,\"y\":16.1112,\"skX\":-101.0785,\"skY\":-101.0785,\"scX\":1.25,\"scY\":1.25}}],\"slot\":[{\"displayIndex\":-1,\"name\":\"blink\",\"parent\":\"root\"},{\"name\":\"back\",\"parent\":\"back\"},{\"name\":\"mid\",\"parent\":\"mid\"},{\"name\":\"face\",\"parent\":\"main\"},{\"name\":\"eyeL\",\"parent\":\"eyeL\"},{\"name\":\"eyeR\",\"parent\":\"eyeR\"},{\"name\":\"eyeHeartL\",\"parent\":\"eyeHeartL\"},{\"name\":\"eyeHeartR\",\"parent\":\"eyeHeartR\"},{\"name\":\"eyebrowL\",\"parent\":\"eyebrowL\"},{\"name\":\"eyebrowR\",\"parent\":\"eyebrowR\"},{\"name\":\"mouth\",\"parent\":\"mouth\"},{\"displayIndex\":-1,\"name\":\"COS0\",\"parent\":\"main\"},{\"displayIndex\":-1,\"name\":\"eyeCover\",\"parent\":\"eyeCover\"},{\"displayIndex\":-1,\"name\":\"ARMOR\",\"parent\":\"armors\"},{\"displayIndex\":-1,\"name\":\"food_light_heart\",\"parent\":\"armor\"},{\"displayIndex\":-1,\"name\":\"food_light_outer\",\"parent\":\"armor\"},{\"displayIndex\":-1,\"name\":\"food_lightning\",\"parent\":\"food_lightning\"},{\"displayIndex\":-1,\"name\":\"food_lightning1\",\"parent\":\"food_lightning1\"}],\"skin\":[{\"slot\":[{\"name\":\"eyeHeartR\",\"display\":[{\"name\":\"eyeHeart\",\"transform\":{\"x\":0.49,\"y\":-0.01,\"scX\":0.3078,\"scY\":0.3078}},{\"name\":\"eyeHeart_red\",\"transform\":{\"x\":0.49,\"y\":-0.01,\"scX\":0.3,\"scY\":0.3}}]},{\"name\":\"eyebrowL\",\"display\":[{\"name\":\"eyebrowL\",\"transform\":{\"x\":7.68,\"y\":0.2,\"skX\":-17.94,\"skY\":-17.94,\"scY\":0.9}}]},{\"name\":\"eyeCover\",\"display\":[{\"name\":\"eyeCover\",\"transform\":{\"x\":4.33,\"y\":-0.54,\"skX\":107.08,\"skY\":107.08}}]},{\"name\":\"eyebrowR\",\"display\":[{\"name\":\"eyebrowR\",\"transform\":{\"x\":5.12,\"y\":-0.04,\"skX\":-156.74,\"skY\":-156.74,\"scX\":0.7,\"scY\":0.7}}]},{\"name\":\"food_lightning1\",\"display\":[{\"name\":\"food_lightning\",\"transform\":{\"x\":-6.02,\"y\":-7.47,\"scX\":0.3939,\"scY\":0.3939}}]},{\"name\":\"face\",\"display\":[{\"name\":\"face0\",\"transform\":{\"x\":71.33,\"y\":1.7,\"skX\":90.72,\"skY\":90.72}},{\"name\":\"face1\",\"transform\":{\"x\":71.26,\"y\":1.93,\"skX\":90.72,\"skY\":90.72}},{\"name\":\"face2\",\"transform\":{\"x\":71.26,\"y\":1.93,\"skX\":90.72,\"skY\":90.72}},{\"name\":\"face3\",\"transform\":{\"x\":70.17,\"y\":1.92,\"skX\":90.72,\"skY\":90.72}}]},{\"name\":\"eyeHeartL\",\"display\":[{\"name\":\"eyeHeart\",\"transform\":{\"x\":0.49,\"y\":-0.01,\"scX\":0.3632,\"scY\":0.3632}},{\"name\":\"eyeHeart_red\",\"transform\":{\"x\":0.49,\"y\":-0.01,\"scX\":0.3,\"scY\":0.3}}]},{\"name\":\"food_light_outer\",\"display\":[{\"name\":\"food_light_outer\",\"transform\":{\"x\":-9.78,\"y\":-7.47},\"path\":\"food_light_inner\"}]},{\"name\":\"mouth\",\"display\":[{\"name\":\"mouth\",\"transform\":{\"x\":1.17,\"y\":3.23}},{\"name\":\"mouth_open\",\"transform\":{\"x\":0.03,\"y\":5.72}},{\"name\":\"mouth_large\",\"transform\":{\"x\":1.2,\"y\":9.21},\"path\":\"mouth_wide\"},{\"name\":\"mouth_bite\",\"transform\":{\"x\":2.26,\"y\":-0.46}}]},{\"name\":\"eyeL\",\"display\":[{\"name\":\"eye0\",\"transform\":{\"x\":-1.37,\"y\":0.68}},{\"name\":\"eye1\",\"transform\":{\"x\":-0.76,\"y\":-0.53}},{\"name\":\"eye2\",\"transform\":{\"x\":-0.45,\"y\":-1.44}},{\"name\":\"eye3\",\"transform\":{\"x\":0.15,\"y\":0.47}}]},{\"name\":\"mid\",\"display\":[{\"name\":\"mid0\",\"transform\":{\"x\":6.64,\"y\":70.93}},{\"name\":\"mid1\",\"transform\":{\"x\":6.63,\"y\":70.92}},{\"name\":\"mid2\",\"transform\":{\"x\":6.63,\"y\":70.92}},{\"name\":\"mid3\",\"transform\":{\"x\":6.63,\"y\":70.92}}]},{\"name\":\"COS0\",\"display\":[{\"name\":\"cos_fire\",\"transform\":{\"x\":58.97,\"y\":-11.66,\"skX\":90.72,\"skY\":90.72}}]},{\"name\":\"back\",\"display\":[{\"name\":\"back0\",\"transform\":{\"x\":-55.03,\"y\":3.66}},{\"name\":\"back1\",\"transform\":{\"x\":-55.03,\"y\":3.66}},{\"name\":\"back2\",\"transform\":{\"x\":-55.03,\"y\":3.66}},{\"name\":\"back3\",\"transform\":{\"x\":-55.03,\"y\":3.66}}]},{\"name\":\"eyeR\",\"display\":[{\"name\":\"eye0\",\"transform\":{\"x\":-1.37,\"y\":0.68}},{\"name\":\"eye1\",\"transform\":{\"x\":-0.76,\"y\":-0.53}},{\"name\":\"eye2\",\"transform\":{\"x\":-0.45,\"y\":-1.44}},{\"name\":\"eye3\",\"transform\":{\"x\":0.15,\"y\":0.47}}]},{\"name\":\"ARMOR\",\"display\":[{\"type\":\"armature\",\"name\":\"armor0\",\"transform\":{\"skX\":0.72,\"skY\":0.72}},{\"type\":\"armature\",\"name\":\"armor1\",\"transform\":{\"skX\":0.72,\"skY\":0.72}},{\"type\":\"armature\",\"name\":\"armor2\",\"transform\":{\"skX\":0.72,\"skY\":0.72}}]},{\"name\":\"food_lightning\",\"display\":[{\"name\":\"food_lightning\",\"transform\":{\"x\":-6.02,\"y\":-7.47,\"scX\":0.3939,\"scY\":0.3939}}]},{\"name\":\"food_light_heart\",\"display\":[{\"name\":\"food_light_heart\",\"transform\":{\"x\":-11.63,\"y\":-11.15},\"path\":\"food_light_outer\"}]},{\"name\":\"blink\",\"display\":[{\"type\":\"armature\",\"name\":\"blink\",\"transform\":{\"x\":-4.56,\"y\":-92.31,\"scX\":1.2954,\"scY\":1.2954}}]}]}],\"animation\":[{\"duration\":90,\"playTimes\":0,\"name\":\"Rand11\",\"bone\":[{\"name\":\"eyeL\",\"scaleFrame\":[{\"duration\":3,\"curve\":[0.5,0,0.5,1]},{\"duration\":3,\"curve\":[0.5,0,0.5,1]},{\"duration\":4,\"curve\":[0.5,0,0.5,1],\"y\":1.2},{\"duration\":24,\"curve\":[0.5,0,0.5,1],\"y\":1.1},{\"duration\":6,\"curve\":[0.5,0,0.5,1],\"y\":1.1},{\"duration\":50}]},{\"name\":\"eyeR\",\"scaleFrame\":[{\"duration\":3,\"curve\":[0.5,0,0.5,1]},{\"duration\":3,\"curve\":[0.5,0,0.5,1]},{\"duration\":4,\"curve\":[0.5,0,0.5,1],\"y\":1.25},{\"duration\":24,\"curve\":[0.5,0,0.5,1],\"y\":1.13},{\"duration\":6,\"curve\":[0.5,0,0.5,1],\"y\":1.13},{\"duration\":50}]},{\"name\":\"eyeHeartL\",\"translateFrame\":[{\"duration\":10},{\"duration\":2,\"curve\":[0.5,0,0.5,1]},{\"duration\":10,\"curve\":[0.5,0,0.5,1],\"x\":-21.16},{\"curve\":[0.5,0,0.5,1],\"x\":-21.16},{\"duration\":2,\"curve\":[0.5,0,0.5,1],\"x\":-18.16},{\"duration\":12,\"curve\":[0.5,0,0.5,1],\"x\":6.84},{\"curve\":[0.5,0,0.5,1],\"x\":6.84},{\"duration\":52}],\"scaleFrame\":[{\"duration\":10},{\"curve\":[0.5,0,0.5,1]},{\"curve\":[0.5,0,0.5,1],\"x\":4,\"y\":0.75},{\"duration\":10,\"curve\":[0.5,0,0.5,1]},{\"duration\":2,\"curve\":[0.5,0,0.5,1]},{\"curve\":[0.5,0,0.5,1],\"x\":5,\"y\":0.6},{\"duration\":65}]},{\"name\":\"eyeHeartR\",\"translateFrame\":[{\"duration\":10},{\"duration\":2,\"curve\":[0.5,0,0.5,1]},{\"duration\":10,\"curve\":[0.5,0,0.5,1],\"x\":-4},{\"duration\":3,\"curve\":[0.5,0,0.5,1],\"x\":-4},{\"duration\":12,\"curve\":[0.5,0,0.5,1],\"x\":18},{\"curve\":[0.5,0,0.5,1],\"x\":18},{\"duration\":52}],\"scaleFrame\":[{\"duration\":11},{\"curve\":[0.5,0,0.5,1],\"x\":2.8,\"y\":0.6},{\"duration\":10,\"curve\":[0.5,0,0.5,1]},{\"curve\":[0.5,0,0.5,1]},{\"duration\":2,\"curve\":[0.5,0,0.5,1],\"x\":3,\"y\":0.8},{\"duration\":65}]},{\"name\":\"eyebrowL\",\"translateFrame\":[{\"duration\":31},{\"duration\":3,\"curve\":[0.5,0,0.5,1]},{\"duration\":3,\"curve\":[0.5,0,0.5,1],\"y\":4},{\"duration\":3,\"curve\":[0.5,0,0.5,1],\"y\":4},{\"duration\":50}]},{\"name\":\"eyebrowR\",\"translateFrame\":[{\"duration\":31},{\"duration\":3,\"curve\":[0.5,0,0.5,1]},{\"duration\":3,\"curve\":[0.5,0,0.5,1],\"y\":4},{\"duration\":3,\"curve\":[0.5,0,0.5,1],\"y\":4},{\"duration\":50}]},{\"name\":\"mouth\",\"translateFrame\":[{\"duration\":3},{\"duration\":3,\"curve\":[0.5,0,0.5,1]},{\"duration\":31,\"curve\":[0.5,0,0.5,1],\"y\":4},{\"duration\":3,\"curve\":[0.5,0,0.5,1],\"y\":4},{\"duration\":50}]}],\"slot\":[{\"name\":\"eyeL\",\"displayFrame\":[{\"duration\":32},{\"value\":1},{\"value\":2},{\"duration\":4,\"value\":3},{\"value\":2},{\"value\":1},{\"duration\":50}]},{\"name\":\"eyeR\",\"displayFrame\":[{\"duration\":32},{\"value\":1},{\"value\":2},{\"duration\":4,\"value\":3},{\"value\":2},{\"value\":1},{\"duration\":50}]},{\"name\":\"eyeHeartL\",\"displayFrame\":[{\"duration\":34},{\"duration\":4,\"value\":-1},{\"duration\":52}]},{\"name\":\"eyeHeartR\",\"displayFrame\":[{\"duration\":34},{\"duration\":4,\"value\":-1},{\"duration\":52}]}]},{\"duration\":90,\"playTimes\":0,\"name\":\"Idle1\",\"slot\":[{\"name\":\"eyeL\",\"displayFrame\":[{},{\"value\":1},{\"value\":2},{\"duration\":4,\"value\":3},{\"value\":2},{\"value\":1},{\"duration\":81}]},{\"name\":\"eyeR\",\"displayFrame\":[{},{\"value\":1},{\"value\":2},{\"duration\":4,\"value\":3},{\"value\":2},{\"value\":1},{\"duration\":81}]},{\"name\":\"eyeHeartL\",\"displayFrame\":[{\"duration\":3},{\"duration\":4,\"value\":-1},{\"duration\":83}]},{\"name\":\"eyeHeartR\",\"displayFrame\":[{\"duration\":3},{\"duration\":4,\"value\":-1},{\"duration\":83}]}]},{\"duration\":57,\"playTimes\":0,\"name\":\"Rand21\",\"bone\":[{\"name\":\"eyeL\",\"scaleFrame\":[{\"duration\":3,\"curve\":[0.5,0,0.5,1]},{\"duration\":3,\"curve\":[0.5,0,0.5,1]},{\"duration\":4,\"curve\":[0.5,0,0.5,1],\"y\":1.2},{\"duration\":41,\"curve\":[0.5,0,0.5,1],\"y\":1.1},{\"duration\":3,\"curve\":[0.5,0,0.5,1],\"y\":1.1},{\"duration\":3,\"curve\":[0.5,0,0.5,1],\"y\":0.89},{\"duration\":0}]},{\"name\":\"eyeR\",\"scaleFrame\":[{\"duration\":3,\"curve\":[0.5,0,0.5,1]},{\"duration\":3,\"curve\":[0.5,0,0.5,1]},{\"duration\":4,\"curve\":[0.5,0,0.5,1],\"y\":1.25},{\"duration\":41,\"curve\":[0.5,0,0.5,1],\"y\":1.1},{\"duration\":3,\"curve\":[0.5,0,0.5,1],\"y\":1.1},{\"duration\":3,\"curve\":[0.5,0,0.5,1],\"y\":0.89},{\"duration\":0}]},{\"name\":\"eyeHeartL\",\"translateFrame\":[{\"duration\":10},{\"duration\":2,\"curve\":[0.5,0,0.5,1]},{\"duration\":10,\"curve\":[0.5,0,0.5,1],\"x\":-21.16},{\"curve\":[0.5,0,0.5,1],\"x\":-21.16},{\"duration\":2,\"curve\":[0.5,0,0.5,1],\"x\":-18.16},{\"duration\":8,\"curve\":[0.5,0,0.5,1],\"x\":6.84},{\"duration\":2,\"curve\":[0.5,0,0.5,1],\"x\":6.84},{\"duration\":10,\"curve\":[0.5,0,0.5,1],\"x\":-21.16},{\"curve\":[0.5,0,0.5,1],\"x\":-21.16},{\"duration\":2,\"curve\":[0.5,0,0.5,1],\"x\":-18.16},{\"duration\":4,\"curve\":[0.5,0,0.5,1],\"x\":6.84},{\"duration\":2,\"tweenEasing\":0,\"x\":6.84},{\"duration\":3}],\"scaleFrame\":[{\"duration\":10},{\"curve\":[0.5,0,0.5,1]},{\"curve\":[0.5,0,0.5,1],\"x\":4,\"y\":0.75},{\"duration\":10,\"curve\":[0.5,0,0.5,1]},{\"duration\":2,\"curve\":[0.5,0,0.5,1]},{\"curve\":[0.5,0,0.5,1],\"x\":5,\"y\":0.6},{\"duration\":8,\"curve\":[0.5,0,0.5,1]},{\"curve\":[0.5,0,0.5,1]},{\"curve\":[0.5,0,0.5,1],\"x\":4,\"y\":0.75},{\"duration\":10,\"curve\":[0.5,0,0.5,1]},{\"duration\":2,\"curve\":[0.5,0,0.5,1]},{\"curve\":[0.5,0,0.5,1],\"x\":5,\"y\":0.6},{\"duration\":9}]},{\"name\":\"eyeHeartR\",\"translateFrame\":[{\"duration\":10},{\"duration\":2,\"curve\":[0.5,0,0.5,1]},{\"duration\":10,\"curve\":[0.5,0,0.5,1],\"x\":-4},{\"duration\":3,\"curve\":[0.5,0,0.5,1],\"x\":-4},{\"duration\":8,\"curve\":[0.5,0,0.5,1],\"x\":18},{\"duration\":2,\"curve\":[0.5,0,0.5,1],\"x\":18},{\"duration\":10,\"curve\":[0.5,0,0.5,1],\"x\":-4},{\"duration\":3,\"curve\":[0.5,0,0.5,1],\"x\":-4},{\"duration\":4,\"curve\":[0.5,0,0.5,1],\"x\":18},{\"duration\":2,\"curve\":[0.5,0,0.5,1],\"x\":18},{\"duration\":3}],\"scaleFrame\":[{\"duration\":11},{\"curve\":[0.5,0,0.5,1],\"x\":2.8,\"y\":0.6},{\"duration\":10,\"curve\":[0.5,0,0.5,1]},{\"curve\":[0.5,0,0.5,1]},{\"duration\":2,\"curve\":[0.5,0,0.5,1],\"x\":3,\"y\":0.8},{\"duration\":8,\"curve\":[0.5,0,0.5,1]},{\"curve\":[0.5,0,0.5,1]},{\"curve\":[0.5,0,0.5,1],\"x\":2.8,\"y\":0.6},{\"duration\":10,\"curve\":[0.5,0,0.5,1]},{\"curve\":[0.5,0,0.5,1]},{\"duration\":2,\"curve\":[0.5,0,0.5,1],\"x\":3,\"y\":0.8},{\"duration\":9}]},{\"name\":\"eyebrowL\",\"translateFrame\":[{\"duration\":3,\"curve\":[0.5,0,0.5,1]},{\"duration\":3,\"curve\":[0.5,0,0.5,1]},{\"duration\":3,\"curve\":[0.5,0,0.5,1],\"y\":-3.8},{\"duration\":41,\"tweenEasing\":0,\"y\":-1.71},{\"duration\":4,\"curve\":[0.5,0,0.5,1],\"y\":-1.71},{\"duration\":3,\"curve\":[0.5,0,0.5,1],\"y\":2.63},{\"duration\":0}]},{\"name\":\"eyebrowR\",\"translateFrame\":[{\"duration\":3,\"tweenEasing\":0,\"y\":7},{\"duration\":3,\"curve\":[0.5,0,0.5,1],\"y\":7},{\"duration\":3,\"curve\":[0.5,0,0.5,1],\"y\":-2.04},{\"duration\":41,\"tweenEasing\":0,\"y\":0.62},{\"duration\":4,\"curve\":[0.5,0,0.5,1],\"y\":0.62},{\"duration\":3,\"curve\":[0.5,0,0.5,1],\"y\":9.34},{\"duration\":0,\"y\":7}]},{\"name\":\"mouth\",\"translateFrame\":[{\"duration\":3},{\"duration\":3,\"curve\":[0.5,0,0.5,1]},{\"duration\":44,\"curve\":[0.5,0,0.5,1],\"y\":4},{\"duration\":4,\"curve\":[0.5,0,0.5,1],\"y\":4},{\"duration\":3,\"curve\":[0.5,0,0.5,1],\"y\":-1.44},{\"duration\":0}]}],\"slot\":[{\"name\":\"face\",\"displayFrame\":[{\"duration\":57,\"value\":1}]},{\"name\":\"mid\",\"displayFrame\":[{\"duration\":57,\"value\":1}]},{\"name\":\"back\",\"displayFrame\":[{\"duration\":57,\"value\":1}]},{\"name\":\"mouth\",\"displayFrame\":[{\"duration\":57,\"value\":1}]}]},{\"duration\":70,\"playTimes\":0,\"name\":\"Rand22\",\"bone\":[{\"name\":\"eyeL\",\"translateFrame\":[{\"duration\":2},{\"duration\":3,\"tweenEasing\":0},{\"duration\":2,\"tweenEasing\":0,\"y\":2},{\"duration\":4,\"tweenEasing\":0,\"y\":6},{\"duration\":2,\"tweenEasing\":0,\"y\":2},{\"duration\":4,\"tweenEasing\":0,\"y\":6},{\"duration\":2,\"tweenEasing\":0,\"y\":2},{\"duration\":4,\"tweenEasing\":0,\"y\":6},{\"duration\":2,\"tweenEasing\":0,\"y\":2},{\"duration\":4,\"tweenEasing\":0,\"y\":6},{\"duration\":2,\"tweenEasing\":0,\"y\":2},{\"duration\":4,\"tweenEasing\":0,\"y\":6},{\"duration\":5,\"tweenEasing\":0,\"y\":2},{\"duration\":30}],\"scaleFrame\":[{},{\"tweenEasing\":0,\"y\":1.1},{\"duration\":68}]},{\"name\":\"eyeR\",\"translateFrame\":[{\"duration\":2},{\"duration\":3,\"tweenEasing\":0},{\"duration\":2,\"tweenEasing\":0,\"y\":3.05},{\"duration\":4,\"tweenEasing\":0,\"y\":7.05},{\"duration\":2,\"tweenEasing\":0,\"y\":3.05},{\"duration\":4,\"tweenEasing\":0,\"y\":7.05},{\"duration\":2,\"tweenEasing\":0,\"y\":3.05},{\"duration\":4,\"tweenEasing\":0,\"y\":7.05},{\"duration\":2,\"tweenEasing\":0,\"y\":3.05},{\"duration\":4,\"tweenEasing\":0,\"y\":7.05},{\"duration\":2,\"tweenEasing\":0,\"y\":3.05},{\"duration\":4,\"tweenEasing\":0,\"y\":7.05},{\"duration\":5,\"tweenEasing\":0,\"y\":3.05},{\"duration\":30}],\"scaleFrame\":[{},{\"tweenEasing\":0,\"y\":1.13},{\"duration\":68}]},{\"name\":\"eyebrowL\",\"translateFrame\":[{\"duration\":2},{\"duration\":3,\"curve\":[0.5,0,0.5,1],\"y\":4},{\"duration\":2,\"tweenEasing\":0,\"y\":4},{\"duration\":4,\"tweenEasing\":0,\"y\":11},{\"duration\":2,\"tweenEasing\":0,\"y\":4},{\"duration\":4,\"tweenEasing\":0,\"y\":11},{\"duration\":2,\"tweenEasing\":0,\"y\":4},{\"duration\":4,\"tweenEasing\":0,\"y\":11},{\"duration\":2,\"tweenEasing\":0,\"y\":4},{\"duration\":4,\"tweenEasing\":0,\"y\":11},{\"duration\":2,\"tweenEasing\":0,\"y\":4},{\"duration\":4,\"tweenEasing\":0,\"y\":11},{\"duration\":5,\"tweenEasing\":0,\"y\":4},{\"duration\":30}]},{\"name\":\"eyebrowR\",\"translateFrame\":[{\"duration\":2},{\"duration\":3,\"tweenEasing\":0},{\"duration\":2,\"tweenEasing\":0,\"y\":7},{\"duration\":4,\"tweenEasing\":0,\"y\":14},{\"duration\":2,\"tweenEasing\":0,\"y\":7},{\"duration\":4,\"tweenEasing\":0,\"y\":14},{\"duration\":2,\"tweenEasing\":0,\"y\":7},{\"duration\":4,\"tweenEasing\":0,\"y\":14},{\"duration\":2,\"tweenEasing\":0,\"y\":7},{\"duration\":4,\"tweenEasing\":0,\"y\":14},{\"duration\":2,\"tweenEasing\":0,\"y\":7},{\"duration\":4,\"tweenEasing\":0,\"y\":14},{\"duration\":35,\"y\":7}]},{\"name\":\"mouth\",\"translateFrame\":[{\"duration\":5,\"curve\":[0.5,0,0.5,1],\"y\":4},{\"duration\":3,\"tweenEasing\":0},{\"duration\":3,\"tweenEasing\":0,\"y\":6},{\"duration\":3,\"tweenEasing\":0},{\"duration\":3,\"tweenEasing\":0,\"y\":6},{\"duration\":3,\"tweenEasing\":0},{\"duration\":3,\"tweenEasing\":0,\"y\":6},{\"duration\":3,\"tweenEasing\":0},{\"duration\":3,\"tweenEasing\":0,\"y\":6},{\"duration\":3,\"tweenEasing\":0},{\"duration\":3,\"tweenEasing\":0,\"y\":6},{\"duration\":35}],\"scaleFrame\":[{\"duration\":5},{\"duration\":3,\"tweenEasing\":0},{\"duration\":3,\"tweenEasing\":0,\"x\":1.3,\"y\":0.8},{\"duration\":3,\"tweenEasing\":0},{\"duration\":3,\"tweenEasing\":0,\"x\":1.3,\"y\":0.8},{\"duration\":3,\"tweenEasing\":0},{\"duration\":3,\"tweenEasing\":0,\"x\":1.3,\"y\":0.8},{\"duration\":3,\"tweenEasing\":0},{\"duration\":3,\"tweenEasing\":0,\"x\":1.3,\"y\":0.8},{\"duration\":3,\"tweenEasing\":0},{\"duration\":3,\"tweenEasing\":0,\"x\":1.3,\"y\":0.8},{\"duration\":35}]},{\"name\":\"main\",\"scaleFrame\":[{\"duration\":5},{\"duration\":2,\"tweenEasing\":0},{\"duration\":4,\"tweenEasing\":0,\"x\":0.95,\"y\":1.05},{\"duration\":2,\"tweenEasing\":0},{\"duration\":4,\"tweenEasing\":0,\"x\":0.95,\"y\":1.05},{\"duration\":2,\"tweenEasing\":0},{\"duration\":4,\"tweenEasing\":0,\"x\":0.95,\"y\":1.05},{\"duration\":2,\"tweenEasing\":0},{\"duration\":4,\"tweenEasing\":0,\"x\":0.95,\"y\":1.05},{\"duration\":2,\"tweenEasing\":0},{\"duration\":4,\"tweenEasing\":0,\"x\":0.95,\"y\":1.05},{\"duration\":35}]}],\"slot\":[{\"name\":\"back\",\"displayFrame\":[{\"duration\":70,\"value\":1}]},{\"name\":\"mid\",\"displayFrame\":[{\"duration\":70,\"value\":1}]},{\"name\":\"face\",\"displayFrame\":[{\"duration\":70,\"value\":1}]},{\"name\":\"eyeL\",\"displayFrame\":[{\"value\":1},{\"value\":2},{\"duration\":34,\"value\":3},{\"value\":2},{\"value\":1},{\"duration\":32}]},{\"name\":\"eyeR\",\"displayFrame\":[{\"value\":1},{\"value\":2},{\"duration\":34,\"value\":3},{\"value\":2},{\"value\":1},{\"duration\":32}]},{\"name\":\"eyeHeartL\",\"displayFrame\":[{\"duration\":2},{\"duration\":34,\"value\":-1},{\"duration\":34}]},{\"name\":\"eyeHeartR\",\"displayFrame\":[{\"duration\":2},{\"duration\":34,\"value\":-1},{\"duration\":34}]},{\"name\":\"mouth\",\"displayFrame\":[{\"duration\":5,\"value\":1},{\"duration\":34},{\"duration\":31,\"value\":1}]}]},{\"duration\":50,\"playTimes\":0,\"name\":\"Idle3\",\"bone\":[{\"name\":\"eyeL\",\"translateFrame\":[{\"duration\":20,\"curve\":[0.5,0,0.5,1]},{\"duration\":30,\"curve\":[0.5,0,0.5,1],\"y\":-2},{\"duration\":0}]},{\"name\":\"eyeR\",\"translateFrame\":[{\"duration\":20,\"curve\":[0.5,0,0.5,1]},{\"duration\":30,\"curve\":[0.5,0,0.5,1],\"y\":-2},{\"duration\":0}]},{\"name\":\"eyeHeartL\",\"translateFrame\":[{\"duration\":20,\"curve\":[0.5,0,0.5,1]},{\"duration\":30,\"curve\":[0.5,0,0.5,1],\"y\":-2},{\"duration\":0}]},{\"name\":\"eyeHeartR\",\"translateFrame\":[{\"duration\":20,\"curve\":[0.5,0,0.5,1]},{\"duration\":30,\"curve\":[0.5,0,0.5,1],\"y\":-2},{\"duration\":0}]},{\"name\":\"eyebrowL\",\"translateFrame\":[{\"duration\":20,\"curve\":[0.5,0,0.5,1]},{\"duration\":30,\"curve\":[0.5,0,0.5,1],\"y\":-2},{\"duration\":0}]},{\"name\":\"eyebrowR\",\"translateFrame\":[{\"duration\":20,\"curve\":[0.5,0,0.5,1],\"y\":7},{\"duration\":30,\"curve\":[0.5,0,0.5,1],\"y\":5},{\"duration\":0,\"y\":7}]},{\"name\":\"mouth\",\"translateFrame\":[{\"duration\":20,\"curve\":[0.5,0,0.5,1]},{\"duration\":30,\"curve\":[0.5,0,0.5,1],\"y\":-4},{\"duration\":0}],\"scaleFrame\":[{\"duration\":20,\"curve\":[0.5,0,0.5,1]},{\"duration\":30,\"curve\":[0.5,0,0.5,1],\"x\":1.2,\"y\":0.65},{\"duration\":0}]},{\"name\":\"eyeCover\",\"translateFrame\":[{\"duration\":20,\"curve\":[0.5,0,0.5,1]},{\"duration\":30,\"curve\":[0.5,0,0.5,1],\"x\":0.06,\"y\":-0.9},{\"duration\":0}],\"scaleFrame\":[{\"duration\":20,\"curve\":[0.5,0,0.5,1]},{\"duration\":30,\"curve\":[0.5,0,0.5,1],\"x\":1.16,\"y\":1.09},{\"duration\":0}]}],\"slot\":[{\"name\":\"back\",\"displayFrame\":[{\"duration\":50,\"value\":2}]},{\"name\":\"mid\",\"displayFrame\":[{\"duration\":50,\"value\":2}]},{\"name\":\"face\",\"displayFrame\":[{\"duration\":50,\"value\":2}]},{\"name\":\"mouth\",\"displayFrame\":[{\"duration\":50,\"value\":2}]},{\"name\":\"eyeCover\",\"displayFrame\":[{\"duration\":50}]}]},{\"duration\":50,\"playTimes\":0,\"name\":\"Rand31\",\"bone\":[{\"name\":\"eyeL\",\"translateFrame\":[{\"duration\":20,\"curve\":[0.5,0,0.5,1]},{\"duration\":30,\"curve\":[0.5,0,0.5,1],\"y\":-2},{\"duration\":0}],\"scaleFrame\":[{\"tweenEasing\":0},{\"tweenEasing\":0,\"y\":0.8},{\"duration\":5,\"tweenEasing\":0},{\"tweenEasing\":0},{\"tweenEasing\":0,\"y\":0.8},{\"duration\":41}]},{\"name\":\"eyeR\",\"translateFrame\":[{\"duration\":20,\"curve\":[0.5,0,0.5,1]},{\"duration\":30,\"curve\":[0.5,0,0.5,1],\"y\":-2},{\"duration\":0}],\"scaleFrame\":[{\"tweenEasing\":0},{\"tweenEasing\":0,\"y\":0.81},{\"duration\":5,\"tweenEasing\":0},{\"tweenEasing\":0},{\"tweenEasing\":0,\"y\":0.81},{\"duration\":41}]},{\"name\":\"eyeHeartL\",\"translateFrame\":[{\"duration\":20,\"curve\":[0.5,0,0.5,1]},{\"duration\":30,\"curve\":[0.5,0,0.5,1],\"y\":-2},{\"duration\":0}]},{\"name\":\"eyeHeartR\",\"translateFrame\":[{\"duration\":20,\"curve\":[0.5,0,0.5,1]},{\"duration\":30,\"curve\":[0.5,0,0.5,1],\"y\":-2},{\"duration\":0}]},{\"name\":\"eyebrowL\",\"translateFrame\":[{\"duration\":2,\"curve\":[0.5,0,0.5,1]},{\"duration\":5,\"tweenEasing\":0,\"y\":4},{\"duration\":2,\"tweenEasing\":0,\"y\":4},{\"duration\":11,\"tweenEasing\":0},{\"duration\":30,\"curve\":[0.5,0,0.5,1],\"y\":-2},{\"duration\":0}]},{\"name\":\"eyebrowR\",\"translateFrame\":[{\"duration\":2,\"curve\":[0.5,0,0.5,1],\"y\":7},{\"duration\":5,\"tweenEasing\":0,\"y\":11},{\"duration\":2,\"tweenEasing\":0,\"y\":11},{\"duration\":11,\"tweenEasing\":0,\"y\":7},{\"duration\":30,\"curve\":[0.5,0,0.5,1],\"y\":5},{\"duration\":0,\"y\":7}]},{\"name\":\"mouth\",\"translateFrame\":[{\"duration\":20,\"curve\":[0.5,0,0.5,1]},{\"duration\":30,\"curve\":[0.5,0,0.5,1],\"y\":-4},{\"duration\":0}],\"scaleFrame\":[{\"duration\":20,\"curve\":[0.5,0,0.5,1]},{\"duration\":30,\"curve\":[0.5,0,0.5,1],\"x\":1.2,\"y\":0.65},{\"duration\":0}]},{\"name\":\"eyeCover\",\"translateFrame\":[{\"duration\":20,\"curve\":[0.5,0,0.5,1]},{\"duration\":30,\"curve\":[0.5,0,0.5,1],\"x\":0.99,\"y\":-0.8},{\"duration\":0}],\"scaleFrame\":[{\"duration\":20,\"curve\":[0.5,0,0.5,1]},{\"duration\":30,\"curve\":[0.5,0,0.5,1],\"x\":1.16,\"y\":1.16},{\"duration\":0}]}],\"slot\":[{\"name\":\"back\",\"displayFrame\":[{\"duration\":50,\"value\":2}]},{\"name\":\"mid\",\"displayFrame\":[{\"duration\":50,\"value\":2}]},{\"name\":\"face\",\"displayFrame\":[{\"duration\":50,\"value\":2}]},{\"name\":\"eyeL\",\"displayFrame\":[{\"duration\":2},{\"duration\":6,\"value\":3},{\"duration\":42}]},{\"name\":\"eyeR\",\"displayFrame\":[{\"duration\":2},{\"duration\":6,\"value\":3},{\"duration\":42}]},{\"name\":\"eyeHeartL\",\"displayFrame\":[{\"duration\":2},{\"duration\":6,\"value\":-1},{\"duration\":42}]},{\"name\":\"eyeHeartR\",\"displayFrame\":[{\"duration\":2},{\"duration\":6,\"value\":-1},{\"duration\":42}]},{\"name\":\"mouth\",\"displayFrame\":[{\"duration\":50,\"value\":2}]},{\"name\":\"eyeCover\",\"displayFrame\":[{\"duration\":2},{\"duration\":6,\"value\":-1},{\"duration\":42}]}]},{\"duration\":8,\"playTimes\":0,\"name\":\"Idle4\",\"bone\":[{\"name\":\"eyeL\",\"translateFrame\":[{\"duration\":5,\"curve\":[0,0,0.5,1]},{\"duration\":3,\"curve\":[0,0,0.5,1],\"y\":4},{\"duration\":0}]},{\"name\":\"eyeR\",\"translateFrame\":[{\"duration\":5,\"curve\":[0,0,0.5,1],\"y\":4},{\"duration\":3,\"curve\":[0,0,0.5,1],\"y\":9},{\"duration\":0,\"y\":4}]},{\"name\":\"eyeHeartL\",\"translateFrame\":[{\"duration\":5,\"curve\":[0,0,0.5,1],\"x\":5,\"y\":-3},{\"duration\":3,\"curve\":[0,0,0.5,1],\"x\":5,\"y\":1},{\"duration\":0,\"x\":5,\"y\":-3}]},{\"name\":\"eyebrowL\",\"translateFrame\":[{\"duration\":5,\"curve\":[0,0,0.5,1],\"x\":4,\"y\":-7},{\"duration\":3,\"curve\":[0,0,0.5,1],\"x\":4,\"y\":-3},{\"duration\":0,\"x\":4,\"y\":-7}],\"rotateFrame\":[{\"duration\":8,\"rotate\":11}]},{\"name\":\"eyebrowR\",\"translateFrame\":[{\"duration\":5,\"curve\":[0,0,0.5,1],\"y\":9},{\"duration\":3,\"curve\":[0,0,0.5,1],\"y\":13},{\"duration\":0,\"y\":9}],\"rotateFrame\":[{\"duration\":8,\"rotate\":-28}]},{\"name\":\"mouth\",\"translateFrame\":[{\"duration\":4,\"curve\":[0,0,0.5,1]},{\"duration\":4,\"curve\":[0,0,0.5,1],\"y\":6},{\"duration\":0}],\"scaleFrame\":[{\"duration\":4,\"curve\":[0,0,0.5,1]},{\"duration\":4,\"curve\":[0,0,0.5,1],\"x\":1.3,\"y\":0.8},{\"duration\":0}]},{\"name\":\"main\",\"scaleFrame\":[{\"duration\":5,\"curve\":[0,0,0.5,1]},{\"duration\":3,\"curve\":[0,0,0.5,1],\"x\":0.95,\"y\":1.05},{\"duration\":0}]}],\"slot\":[{\"name\":\"back\",\"displayFrame\":[{\"duration\":8,\"value\":3}]},{\"name\":\"mid\",\"displayFrame\":[{\"duration\":8,\"value\":3}]},{\"name\":\"face\",\"displayFrame\":[{\"duration\":8,\"value\":3}]},{\"name\":\"eyeR\",\"displayFrame\":[{\"duration\":8,\"value\":3}]},{\"name\":\"eyeHeartL\",\"displayFrame\":[{\"duration\":8,\"value\":1}]},{\"name\":\"eyeHeartR\",\"displayFrame\":[{\"duration\":8,\"value\":-1}]},{\"name\":\"mouth\",\"displayFrame\":[{\"duration\":8,\"value\":3}]},{\"name\":\"blink\",\"displayFrame\":[{\"duration\":8}]}]},{\"duration\":68,\"playTimes\":0,\"name\":\"Water\",\"bone\":[{\"name\":\"main\",\"translateFrame\":[{\"duration\":8},{\"duration\":5,\"curve\":[0,0,0.5,1]},{\"duration\":5,\"curve\":[0.5,0,1,1],\"y\":-50},{\"duration\":50}],\"rotateFrame\":[{\"duration\":28},{\"duration\":5,\"curve\":[0.5,0,0.5,1]},{\"duration\":10,\"curve\":[0.5,0,0.5,1],\"rotate\":11},{\"duration\":10,\"curve\":[0.5,0,0.5,1],\"rotate\":-8},{\"duration\":10,\"curve\":[0.5,0,0.5,1],\"rotate\":11},{\"duration\":5,\"curve\":[0.5,0,0.5,1],\"rotate\":-8},{\"duration\":0}],\"scaleFrame\":[{\"duration\":5,\"curve\":[0,0,0.5,1]},{\"duration\":3,\"curve\":[0,0,0.5,1],\"x\":0.9,\"y\":1.1},{\"duration\":5,\"curve\":[0.5,0,1,1],\"x\":1.04,\"y\":0.97},{\"duration\":5,\"curve\":[0.5,0,1,1]},{\"duration\":5,\"curve\":[0,0,0.5,1],\"x\":1.03,\"y\":0.97},{\"duration\":5,\"curve\":[0.5,0,0.5,1],\"x\":0.9,\"y\":1.1},{\"duration\":5,\"curve\":[0.5,0,0.5,1]},{\"duration\":30,\"tweenEasing\":0,\"x\":0.95,\"y\":1.05},{\"duration\":5,\"tweenEasing\":0,\"x\":0.95,\"y\":1.05},{\"duration\":0}]},{\"name\":\"facial\",\"translateFrame\":[{\"duration\":13,\"tweenEasing\":0},{\"duration\":10,\"tweenEasing\":0,\"x\":8},{\"duration\":45}],\"scaleFrame\":[{\"duration\":5,\"tweenEasing\":0},{\"duration\":63,\"tweenEasing\":0,\"y\":0.9},{\"duration\":0}]},{\"name\":\"eyeHeartR\",\"translateFrame\":[{\"duration\":11},{\"duration\":2,\"tweenEasing\":0},{\"duration\":5,\"tweenEasing\":0,\"y\":-9},{\"duration\":50}]},{\"name\":\"eyeHeartL\",\"translateFrame\":[{\"duration\":11},{\"duration\":2,\"tweenEasing\":0},{\"duration\":5,\"tweenEasing\":0,\"y\":-10},{\"duration\":50,\"y\":-2}]}],\"slot\":[{\"name\":\"eyeL\",\"displayFrame\":[{\"duration\":2},{\"value\":1},{\"value\":2},{\"duration\":7,\"value\":3},{\"value\":2},{\"value\":1},{\"duration\":8},{\"value\":1},{\"value\":2},{\"duration\":43,\"value\":3},{\"value\":2},{\"value\":1},{\"duration\":0}]},{\"name\":\"eyeR\",\"displayFrame\":[{\"duration\":2},{\"value\":1},{\"value\":2},{\"duration\":7,\"value\":3},{\"value\":2},{\"value\":1},{\"duration\":8},{\"value\":1},{\"value\":2},{\"duration\":43,\"value\":3},{\"value\":2},{\"value\":1},{\"duration\":0}]},{\"name\":\"eyeHeartL\",\"displayFrame\":[{\"duration\":4},{\"duration\":7,\"value\":-1},{\"duration\":12},{\"duration\":43,\"value\":-1},{\"duration\":2}]},{\"name\":\"eyeHeartR\",\"displayFrame\":[{\"duration\":4},{\"duration\":7,\"value\":-1},{\"duration\":12},{\"duration\":43,\"value\":-1},{\"duration\":2}]},{\"name\":\"mouth\",\"displayFrame\":[{\"duration\":4},{\"duration\":16,\"value\":1},{\"duration\":16,\"value\":3},{\"duration\":32}]}]},{\"duration\":25,\"playTimes\":0,\"name\":\"Food\",\"frame\":[{\"duration\":13},{\"duration\":12,\"events\":[{\"name\":\"wearArmor\"}]},{\"duration\":0,\"events\":[{\"name\":\"foodEnd\"}]}],\"bone\":[{\"name\":\"food_lightning\",\"translateFrame\":[{\"duration\":2},{\"duration\":2},{\"duration\":2,\"x\":-3.5,\"y\":-104.42},{\"duration\":2,\"x\":-67.95,\"y\":-101.42},{\"duration\":2,\"x\":-74.94,\"y\":7.99},{\"duration\":2,\"x\":-26.48,\"y\":-83.94},{\"duration\":2,\"x\":33.97,\"y\":-17.99},{\"duration\":2,\"x\":-113.92,\"y\":-61.45},{\"duration\":2,\"x\":-22.98,\"y\":47.46},{\"duration\":2,\"x\":-103.92,\"y\":-6},{\"duration\":2,\"x\":-19.99,\"y\":-130.9},{\"duration\":2,\"x\":3,\"y\":-65.45},{\"x\":-65.45,\"y\":-33.48}],\"rotateFrame\":[{\"duration\":2},{\"duration\":2},{\"duration\":2,\"rotate\":-100.76},{\"duration\":2,\"rotate\":119.09},{\"duration\":2,\"rotate\":69.55},{\"duration\":2,\"rotate\":-101.09},{\"duration\":2,\"rotate\":-30.54},{\"duration\":2,\"rotate\":80.33},{\"duration\":2,\"rotate\":12.35},{\"duration\":2,\"rotate\":-59.96},{\"duration\":2,\"rotate\":110.94},{\"duration\":2,\"rotate\":174.49},{\"rotate\":-86.47}]},{\"name\":\"food_lightning1\",\"translateFrame\":[{\"duration\":2},{\"duration\":2},{\"duration\":2,\"x\":-29.48,\"y\":26.48},{\"duration\":2,\"x\":89.93,\"y\":75.94},{\"duration\":2,\"x\":47.46,\"y\":-14.99},{\"duration\":2,\"x\":-52.46,\"y\":76.44},{\"duration\":2,\"x\":27.98,\"y\":-85.94},{\"duration\":2,\"x\":66.45,\"y\":90.43},{\"duration\":2,\"x\":60.45,\"y\":-58.46},{\"duration\":2,\"x\":84.94,\"y\":-28.98},{\"duration\":2,\"x\":-17.49,\"y\":63.95},{\"duration\":2,\"x\":-45.97,\"y\":86.44},{\"x\":58.46,\"y\":-36.97}],\"rotateFrame\":[{\"duration\":2},{\"duration\":2},{\"duration\":2,\"rotate\":127.5},{\"duration\":2,\"rotate\":-102.04},{\"duration\":2,\"rotate\":-92.37},{\"duration\":2,\"rotate\":33.61},{\"duration\":2,\"rotate\":-30.54},{\"duration\":2,\"rotate\":-65.51},{\"duration\":2,\"rotate\":-128.22},{\"duration\":2,\"rotate\":82.78},{\"duration\":2,\"rotate\":-116.42},{\"duration\":2,\"rotate\":-72.93},{\"rotate\":2.01}]}],\"slot\":[{\"name\":\"food_light_heart\",\"displayFrame\":[{\"duration\":2,\"value\":-1},{\"duration\":23}],\"colorFrame\":[{\"duration\":2},{\"duration\":5,\"tweenEasing\":0,\"value\":{\"aM\":0}},{\"duration\":13,\"tweenEasing\":0},{\"duration\":5,\"tweenEasing\":0},{\"duration\":0,\"value\":{\"aM\":0}}]},{\"name\":\"food_light_outer\",\"displayFrame\":[{\"duration\":2,\"value\":-1},{\"duration\":23}],\"colorFrame\":[{\"duration\":2},{\"duration\":5,\"tweenEasing\":0,\"value\":{\"aM\":0}},{\"duration\":13,\"tweenEasing\":0},{\"duration\":5,\"tweenEasing\":0},{\"duration\":0,\"value\":{\"aM\":0}}]},{\"name\":\"food_lightning\",\"displayFrame\":[{\"duration\":2,\"value\":-1},{\"duration\":23}],\"colorFrame\":[{\"duration\":2},{\"duration\":3,\"value\":{\"aM\":0}},{\"duration\":18,\"tweenEasing\":0},{\"duration\":2,\"tweenEasing\":0},{\"duration\":0,\"value\":{\"aM\":0}}]},{\"name\":\"food_lightning1\",\"displayFrame\":[{\"duration\":2,\"value\":-1},{\"duration\":23}],\"colorFrame\":[{\"duration\":2},{\"duration\":3,\"value\":{\"aM\":0}},{\"duration\":18,\"tweenEasing\":0},{\"duration\":2,\"tweenEasing\":0},{\"duration\":0,\"value\":{\"aM\":0}}]}]}],\"defaultActions\":[{\"gotoAndPlay\":\"Rand11\"}]},{\"type\":\"Armature\",\"frameRate\":24,\"name\":\"armor0\",\"aabb\":{\"x\":-87.1,\"y\":-131.31,\"width\":168,\"height\":213},\"bone\":[{\"name\":\"root\"}],\"slot\":[{\"name\":\"armor0\",\"parent\":\"root\"},{\"name\":\"armor_green\",\"parent\":\"root\"},{\"name\":\"armor_green1\",\"parent\":\"root\"},{\"name\":\"armor_green2\",\"parent\":\"root\"}],\"skin\":[{\"slot\":[{\"name\":\"armor0\",\"display\":[{\"name\":\"armor0\",\"transform\":{\"x\":-3.1,\"y\":-24.81}}]},{\"name\":\"armor_green1\",\"display\":[{\"name\":\"armor_green\",\"transform\":{\"x\":17.63,\"y\":65.14}}]},{\"name\":\"armor_green2\",\"display\":[{\"name\":\"armor_green\",\"transform\":{\"x\":-14.17,\"y\":45.98}}]},{\"name\":\"armor_green\",\"display\":[{\"name\":\"armor_green\",\"transform\":{\"x\":48.86,\"y\":41.96}}]}]}],\"animation\":[{\"duration\":0,\"playTimes\":0,\"name\":\"Idle\"}],\"defaultActions\":[{\"gotoAndPlay\":\"Idle\"}]},{\"type\":\"Armature\",\"frameRate\":24,\"name\":\"armor1\",\"aabb\":{\"x\":-87.06,\"y\":-46.05,\"width\":168,\"height\":128},\"bone\":[{\"name\":\"root\"}],\"slot\":[{\"name\":\"armor0\",\"parent\":\"root\"},{\"name\":\"armor_green\",\"parent\":\"root\"},{\"name\":\"armor_green1\",\"parent\":\"root\"},{\"name\":\"armor_green2\",\"parent\":\"root\"}],\"skin\":[{\"slot\":[{\"name\":\"armor_green\",\"display\":[{\"name\":\"armor_green\",\"transform\":{\"x\":48.86,\"y\":41.96},\"path\":\"armor_yellow\"}]},{\"name\":\"armor0\",\"display\":[{\"name\":\"armor1\",\"transform\":{\"x\":-3.06,\"y\":17.95}}]},{\"name\":\"armor_green2\",\"display\":[{\"name\":\"armor_green\",\"transform\":{\"x\":-14.17,\"y\":45.98},\"path\":\"armor_yellow\"}]},{\"name\":\"armor_green1\",\"display\":[{\"name\":\"armor_green\",\"transform\":{\"x\":17.63,\"y\":65.14},\"path\":\"armor_yellow\"}]}]}],\"animation\":[{\"duration\":0,\"playTimes\":0,\"name\":\"Idle\"}],\"defaultActions\":[{\"gotoAndPlay\":\"Idle\"}]},{\"type\":\"Armature\",\"frameRate\":24,\"name\":\"armor2\",\"aabb\":{\"x\":-81.99,\"y\":19.55,\"width\":159,\"height\":62},\"bone\":[{\"name\":\"root\"}],\"slot\":[{\"name\":\"armor0\",\"parent\":\"root\"},{\"name\":\"armor_green\",\"parent\":\"root\"},{\"name\":\"armor_green1\",\"parent\":\"root\"},{\"name\":\"armor_green2\",\"parent\":\"root\"}],\"skin\":[{\"slot\":[{\"name\":\"armor0\",\"display\":[{\"name\":\"armor2\",\"transform\":{\"x\":-2.49,\"y\":50.55}}]},{\"name\":\"armor_green2\",\"display\":[{\"name\":\"armor_green\",\"transform\":{\"x\":-14.17,\"y\":45.98},\"path\":\"armor_red\"}]},{\"name\":\"armor_green1\",\"display\":[{\"name\":\"armor_green\",\"transform\":{\"x\":17.63,\"y\":65.14},\"path\":\"armor_red\"}]},{\"name\":\"armor_green\",\"display\":[{\"name\":\"armor_green\",\"transform\":{\"x\":48.86,\"y\":41.96},\"path\":\"armor_red\"}]}]}],\"animation\":[{\"duration\":0,\"playTimes\":0,\"name\":\"Idle\"}],\"defaultActions\":[{\"gotoAndPlay\":\"Idle\"}]},{\"type\":\"Armature\",\"frameRate\":30,\"name\":\"blink\",\"aabb\":{\"x\":-89,\"y\":-90.5,\"width\":178,\"height\":181},\"bone\":[{\"name\":\"root\"}],\"slot\":[{\"name\":\"blink\",\"parent\":\"root\"}],\"skin\":[{\"slot\":[{\"name\":\"blink\",\"display\":[{\"name\":\"blink\"}]}]}],\"animation\":[{\"duration\":8,\"playTimes\":0,\"name\":\"Idle\",\"bone\":[{\"name\":\"root\",\"scaleFrame\":[{\"duration\":8,\"curve\":[0,0,0.5,1],\"x\":0.51,\"y\":0.51},{\"duration\":0}]}],\"slot\":[{\"name\":\"blink\",\"colorFrame\":[{\"duration\":4,\"tweenEasing\":0,\"value\":{\"aM\":0}},{\"duration\":4,\"tweenEasing\":0},{\"duration\":0,\"value\":{\"aM\":0}}]}]}],\"defaultActions\":[{\"gotoAndPlay\":\"Idle\"}]},{\"type\":\"Armature\",\"frameRate\":30,\"name\":\"Bowling\",\"aabb\":{\"x\":-80.53,\"y\":-139.24,\"width\":148.53,\"height\":161.07},\"bone\":[{\"name\":\"root\"},{\"name\":\"b\",\"parent\":\"root\",\"transform\":{\"y\":-59.75}},{\"length\":146,\"name\":\"main\",\"parent\":\"b\",\"transform\":{\"x\":4.2,\"y\":73.4276,\"skX\":-90.7235,\"skY\":-90.7235}},{\"name\":\"back\",\"parent\":\"main\",\"transform\":{\"x\":68.3976,\"y\":-3.3366,\"skX\":90.7235,\"skY\":90.7235}},{\"name\":\"mid\",\"parent\":\"main\",\"transform\":{\"x\":144.2157,\"y\":-28.6052,\"skX\":90.7235,\"skY\":90.7235}},{\"name\":\"facial\",\"parent\":\"main\",\"transform\":{\"x\":91.4126,\"y\":5.4956,\"skX\":90.7235,\"skY\":90.7235}},{\"name\":\"mouth\",\"parent\":\"facial\",\"transform\":{\"x\":0.0048,\"y\":17.02}},{\"length\":14,\"name\":\"eyebrowL\",\"parent\":\"facial\",\"transform\":{\"x\":-25.7409,\"y\":-30.1344,\"skX\":17.9389,\"skY\":17.9389}},{\"name\":\"eyeL\",\"parent\":\"facial\",\"transform\":{\"x\":-23.3156,\"y\":-3.5144}},{\"length\":11,\"name\":\"eyebrowR\",\"parent\":\"facial\",\"transform\":{\"x\":18.7043,\"y\":-29.683,\"skX\":168.7399,\"skY\":168.7399}},{\"name\":\"eyeR\",\"parent\":\"facial\",\"transform\":{\"x\":22.3987,\"y\":-6.562,\"skX\":-6,\"skY\":-6,\"scX\":0.7656,\"scY\":0.8}},{\"name\":\"eyeHeartL\",\"parent\":\"eyeL\",\"transform\":{\"x\":5.23,\"y\":0.367}},{\"length\":8,\"name\":\"eyeCover\",\"parent\":\"eyeR\",\"transform\":{\"x\":1.0848,\"y\":16.1112,\"skX\":-101.0785,\"skY\":-101.0785,\"scX\":1.25,\"scY\":1.25}},{\"name\":\"eyeHeartR\",\"parent\":\"eyeR\",\"transform\":{\"x\":-10.7202,\"y\":-0.2591,\"skX\":6,\"skY\":6,\"scX\":1.25,\"scY\":1.25}}],\"slot\":[{\"name\":\"back\",\"parent\":\"back\"},{\"name\":\"mid\",\"parent\":\"mid\"},{\"name\":\"face\",\"parent\":\"main\"},{\"name\":\"eyeL\",\"parent\":\"eyeL\"},{\"name\":\"eyeR\",\"parent\":\"eyeR\"},{\"name\":\"eyeHeartL\",\"parent\":\"eyeHeartL\"},{\"name\":\"eyeHeartR\",\"parent\":\"eyeHeartR\"},{\"name\":\"eyebrowL\",\"parent\":\"eyebrowL\"},{\"name\":\"eyebrowR\",\"parent\":\"eyebrowR\"},{\"name\":\"mouth\",\"parent\":\"mouth\"},{\"displayIndex\":-1,\"name\":\"eyeCover\",\"parent\":\"eyeCover\"}],\"skin\":[{\"slot\":[{\"name\":\"eyeHeartR\",\"display\":[{\"name\":\"eyeHeart\",\"transform\":{\"x\":0.49,\"y\":-0.01,\"scX\":0.3078,\"scY\":0.3078}},{\"name\":\"eyeHeart_red\",\"transform\":{\"x\":0.49,\"y\":-0.01,\"scX\":0.3,\"scY\":0.3}}]},{\"name\":\"mouth\",\"display\":[{\"name\":\"mouth\",\"transform\":{\"x\":1.17,\"y\":3.23}},{\"name\":\"mouth_open\",\"transform\":{\"x\":0.03,\"y\":5.72}},{\"name\":\"mouth_large\",\"transform\":{\"x\":1.2,\"y\":9.21},\"path\":\"mouth_wide\"},{\"name\":\"mouth_bite\",\"transform\":{\"x\":2.26,\"y\":-0.46}}]},{\"name\":\"face\",\"display\":[{\"name\":\"face0\",\"transform\":{\"x\":71.33,\"y\":1.7,\"skX\":90.72,\"skY\":90.72}},{\"name\":\"face1\",\"transform\":{\"x\":71.26,\"y\":1.93,\"skX\":90.72,\"skY\":90.72}},{\"name\":\"face2\",\"transform\":{\"x\":71.26,\"y\":1.93,\"skX\":90.72,\"skY\":90.72}},{\"name\":\"face3\",\"transform\":{\"x\":70.17,\"y\":1.92,\"skX\":90.72,\"skY\":90.72}}]},{\"name\":\"eyebrowR\",\"display\":[{\"name\":\"eyebrowR\",\"transform\":{\"x\":5.12,\"y\":-0.04,\"skX\":-156.74,\"skY\":-156.74,\"scX\":0.7,\"scY\":0.7}}]},{\"name\":\"eyeR\",\"display\":[{\"name\":\"eye0\",\"transform\":{\"x\":-1.37,\"y\":0.68}},{\"name\":\"eye1\",\"transform\":{\"x\":-0.76,\"y\":-0.53}},{\"name\":\"eye2\",\"transform\":{\"x\":-0.45,\"y\":-1.44}},{\"name\":\"eye3\",\"transform\":{\"x\":0.15,\"y\":0.47}}]},{\"name\":\"eyebrowL\",\"display\":[{\"name\":\"eyebrowL\",\"transform\":{\"x\":7.68,\"y\":0.2,\"skX\":-17.94,\"skY\":-17.94,\"scY\":0.9}}]},{\"name\":\"back\",\"display\":[{\"name\":\"back0\",\"transform\":{\"x\":-55.03,\"y\":3.66}}]},{\"name\":\"eyeCover\",\"display\":[{\"name\":\"eyeCover\",\"transform\":{\"x\":4.33,\"y\":-0.54,\"skX\":107.08,\"skY\":107.08}}]},{\"name\":\"eyeHeartL\",\"display\":[{\"name\":\"eyeHeart\",\"transform\":{\"x\":0.49,\"y\":-0.01,\"scX\":0.3632,\"scY\":0.3632}},{\"name\":\"eyeHeart_red\",\"transform\":{\"x\":0.49,\"y\":-0.01,\"scX\":0.3,\"scY\":0.3}}]},{\"name\":\"mid\",\"display\":[{\"name\":\"mid0\",\"transform\":{\"x\":6.64,\"y\":70.93}},{\"name\":\"mid1\",\"transform\":{\"x\":6.63,\"y\":70.92}},{\"name\":\"mid2\",\"transform\":{\"x\":6.63,\"y\":70.92}},{\"name\":\"mid3\",\"transform\":{\"x\":6.63,\"y\":70.92}}]},{\"name\":\"eyeL\",\"display\":[{\"name\":\"eye0\",\"transform\":{\"x\":-1.37,\"y\":0.68}},{\"name\":\"eye1\",\"transform\":{\"x\":-0.76,\"y\":-0.53}},{\"name\":\"eye2\",\"transform\":{\"x\":-0.45,\"y\":-1.44}},{\"name\":\"eye3\",\"transform\":{\"x\":0.15,\"y\":0.47}}]}]}],\"animation\":[{\"duration\":90,\"playTimes\":0,\"name\":\"Idle\",\"bone\":[{\"name\":\"b\",\"translateFrame\":[{\"duration\":8,\"tweenEasing\":0},{\"duration\":7,\"tweenEasing\":0,\"y\":14.16},{\"duration\":8,\"tweenEasing\":0,\"y\":-0.33},{\"duration\":7,\"tweenEasing\":0,\"y\":-3.29},{\"duration\":8,\"tweenEasing\":0},{\"duration\":7,\"tweenEasing\":0,\"y\":14.16},{\"duration\":8,\"tweenEasing\":0,\"y\":-0.33},{\"duration\":7,\"tweenEasing\":0,\"y\":-3.29},{\"duration\":8,\"tweenEasing\":0},{\"duration\":7,\"tweenEasing\":0,\"y\":14.16},{\"duration\":8,\"tweenEasing\":0,\"y\":-0.33},{\"duration\":7,\"tweenEasing\":0,\"y\":-3.29},{\"duration\":0}],\"rotateFrame\":[{\"duration\":90,\"tweenEasing\":0,\"clockwise\":4},{\"duration\":0}]}],\"slot\":[{\"name\":\"eyeL\",\"displayFrame\":[{},{\"value\":1},{\"value\":2},{\"duration\":4,\"value\":3},{\"value\":2},{\"value\":1},{\"duration\":81}]},{\"name\":\"eyeR\",\"displayFrame\":[{},{\"value\":1},{\"value\":2},{\"duration\":4,\"value\":3},{\"value\":2},{\"value\":1},{\"duration\":81}]},{\"name\":\"eyeHeartL\",\"displayFrame\":[{\"duration\":3},{\"duration\":4,\"value\":-1},{\"duration\":83}]},{\"name\":\"eyeHeartR\",\"displayFrame\":[{\"duration\":3},{\"duration\":4,\"value\":-1},{\"duration\":83}]}]}],\"defaultActions\":[{\"gotoAndPlay\":\"Idle\"}]}]}"]],0,0,[],[],[]],[[[10,"PlantAnimate_tex","{\"width\":1024,\"height\":512,\"name\":\"PlantAnimate\",\"imagePath\":\"PlantAnimate_tex.png\",\"SubTexture\":[{\"frameHeight\":130,\"y\":129,\"frameWidth\":51,\"frameX\":-2,\"width\":46,\"frameY\":-2,\"height\":126,\"name\":\"back1\",\"x\":751},{\"frameHeight\":130,\"y\":1,\"frameWidth\":51,\"frameX\":-2,\"width\":46,\"frameY\":-2,\"height\":126,\"name\":\"back3\",\"x\":751},{\"frameHeight\":130,\"y\":1,\"frameWidth\":51,\"frameX\":-2,\"width\":46,\"frameY\":-2,\"height\":126,\"name\":\"back2\",\"x\":703},{\"frameHeight\":130,\"y\":129,\"frameWidth\":51,\"frameX\":-2,\"width\":46,\"frameY\":-2,\"height\":126,\"name\":\"back0\",\"x\":703},{\"frameHeight\":160,\"y\":1,\"frameWidth\":94,\"frameX\":-2,\"width\":90,\"frameY\":-2,\"height\":156,\"name\":\"mid0\",\"x\":335},{\"frameHeight\":160,\"y\":1,\"frameWidth\":94,\"frameX\":-2,\"width\":90,\"frameY\":-2,\"height\":156,\"name\":\"mid2\",\"x\":427},{\"frameHeight\":160,\"y\":1,\"frameWidth\":94,\"frameX\":-2,\"width\":90,\"frameY\":-2,\"height\":156,\"name\":\"mid3\",\"x\":611},{\"frameHeight\":160,\"y\":1,\"frameWidth\":94,\"frameX\":-2,\"width\":90,\"frameY\":-2,\"height\":156,\"name\":\"mid1\",\"x\":519},{\"frameHeight\":159,\"y\":158,\"frameWidth\":126,\"frameX\":-2,\"width\":122,\"frameY\":-2,\"height\":155,\"name\":\"face1\",\"x\":875},{\"frameHeight\":159,\"y\":1,\"frameWidth\":126,\"frameX\":-2,\"width\":122,\"frameY\":-2,\"height\":155,\"name\":\"face2\",\"x\":875},{\"frameHeight\":159,\"y\":315,\"frameWidth\":126,\"frameX\":-2,\"width\":122,\"frameY\":-2,\"height\":155,\"name\":\"face0\",\"x\":875},{\"frameHeight\":158,\"y\":1,\"frameWidth\":126,\"frameX\":-2,\"width\":122,\"frameY\":-2,\"height\":154,\"name\":\"face3\",\"x\":211},{\"frameHeight\":42,\"y\":472,\"frameWidth\":44,\"frameX\":-2,\"width\":40,\"frameY\":-2,\"height\":38,\"name\":\"eye1\",\"x\":849},{\"frameHeight\":26,\"y\":472,\"frameWidth\":42,\"frameX\":-2,\"width\":38,\"frameY\":-2,\"height\":22,\"name\":\"eye3\",\"x\":933},{\"frameHeight\":45,\"y\":157,\"frameWidth\":40,\"frameX\":-2,\"width\":36,\"frameY\":-2,\"height\":40,\"name\":\"eye0\",\"x\":211},{\"frameHeight\":42,\"y\":472,\"frameWidth\":44,\"frameX\":-2,\"width\":40,\"frameY\":-2,\"height\":38,\"name\":\"eye2\",\"x\":891},{\"frameHeight\":19,\"y\":157,\"frameWidth\":19,\"frameX\":-2,\"width\":15,\"frameY\":-2,\"height\":15,\"name\":\"eyeHeart_red\",\"x\":282},{\"frameHeight\":17,\"y\":157,\"frameWidth\":17,\"frameX\":-2,\"width\":13,\"frameY\":-2,\"height\":13,\"name\":\"eyeHeart\",\"x\":319},{\"frameHeight\":14,\"y\":157,\"frameWidth\":22,\"frameX\":-2,\"width\":18,\"frameY\":-2,\"height\":10,\"name\":\"eyebrowL\",\"x\":299},{\"frameHeight\":14,\"y\":498,\"frameWidth\":22,\"frameX\":-2,\"width\":18,\"frameY\":-2,\"height\":10,\"name\":\"eyebrowR\",\"x\":993},{\"frameHeight\":37,\"y\":472,\"frameWidth\":22,\"frameX\":-2,\"width\":18,\"frameY\":-2,\"height\":33,\"name\":\"mouth_wide\",\"x\":973},{\"frameHeight\":22,\"y\":157,\"frameWidth\":35,\"frameX\":-2,\"width\":31,\"frameY\":-2,\"height\":18,\"name\":\"mouth_bite\",\"x\":249},{\"frameHeight\":28,\"y\":472,\"frameWidth\":28,\"frameX\":-2,\"width\":24,\"frameY\":-2,\"height\":24,\"name\":\"mouth_open\",\"x\":993},{\"frameHeight\":25,\"y\":375,\"frameWidth\":28,\"frameX\":-2,\"width\":24,\"frameY\":-2,\"height\":21,\"name\":\"mouth\",\"x\":849},{\"frameHeight\":118,\"y\":259,\"frameWidth\":194,\"frameX\":-2,\"width\":190,\"frameY\":-2,\"height\":114,\"name\":\"cos_fire\",\"x\":683},{\"frameHeight\":19,\"y\":496,\"frameWidth\":31,\"frameX\":-2,\"width\":26,\"frameY\":-2,\"height\":15,\"name\":\"eyeCover\",\"x\":933},{\"frameHeight\":272,\"y\":1,\"frameWidth\":229,\"frameX\":-10,\"width\":208,\"frameY\":-10,\"height\":256,\"name\":\"food_light_outer\",\"x\":1},{\"frameHeight\":237,\"y\":259,\"frameWidth\":192,\"frameX\":-6,\"width\":180,\"frameY\":-6,\"height\":225,\"name\":\"food_light_inner\",\"x\":1},{\"frameHeight\":195,\"y\":259,\"frameWidth\":183,\"frameX\":-8,\"width\":165,\"frameY\":-11,\"height\":173,\"name\":\"food_lightning\",\"x\":349},{\"frameHeight\":213,\"y\":259,\"frameWidth\":168,\"frameX\":-2,\"width\":164,\"frameY\":-2,\"height\":209,\"name\":\"armor0\",\"x\":183},{\"frameHeight\":26,\"y\":398,\"frameWidth\":27,\"frameX\":-2,\"width\":22,\"frameY\":-2,\"height\":22,\"name\":\"armor_green\",\"x\":849},{\"frameHeight\":128,\"y\":375,\"frameWidth\":168,\"frameX\":-2,\"width\":164,\"frameY\":-2,\"height\":123,\"name\":\"armor1\",\"x\":683},{\"frameHeight\":26,\"y\":446,\"frameWidth\":27,\"frameX\":-2,\"width\":22,\"frameY\":-2,\"height\":22,\"name\":\"armor_yellow\",\"x\":849},{\"frameHeight\":62,\"y\":430,\"frameWidth\":159,\"frameX\":-2,\"width\":155,\"frameY\":-1,\"height\":59,\"name\":\"armor2\",\"x\":516},{\"frameHeight\":26,\"y\":422,\"frameWidth\":27,\"frameX\":-2,\"width\":22,\"frameY\":-2,\"height\":22,\"name\":\"armor_red\",\"x\":849},{\"frameHeight\":181,\"y\":259,\"frameWidth\":178,\"frameX\":-3,\"width\":165,\"frameY\":-3,\"height\":169,\"name\":\"blink\",\"x\":516}]}",{"width":1024,"height":512,"name":"PlantAnimate","imagePath":"PlantAnimate_tex.png","SubTexture":[{"frameHeight":130,"y":129,"frameWidth":51,"frameX":-2,"width":46,"frameY":-2,"height":126,"name":"back1","x":751},{"frameHeight":130,"y":1,"frameWidth":51,"frameX":-2,"width":46,"frameY":-2,"height":126,"name":"back3","x":751},{"frameHeight":130,"y":1,"frameWidth":51,"frameX":-2,"width":46,"frameY":-2,"height":126,"name":"back2","x":703},{"frameHeight":130,"y":129,"frameWidth":51,"frameX":-2,"width":46,"frameY":-2,"height":126,"name":"back0","x":703},{"frameHeight":160,"y":1,"frameWidth":94,"frameX":-2,"width":90,"frameY":-2,"height":156,"name":"mid0","x":335},{"frameHeight":160,"y":1,"frameWidth":94,"frameX":-2,"width":90,"frameY":-2,"height":156,"name":"mid2","x":427},{"frameHeight":160,"y":1,"frameWidth":94,"frameX":-2,"width":90,"frameY":-2,"height":156,"name":"mid3","x":611},{"frameHeight":160,"y":1,"frameWidth":94,"frameX":-2,"width":90,"frameY":-2,"height":156,"name":"mid1","x":519},{"frameHeight":159,"y":158,"frameWidth":126,"frameX":-2,"width":122,"frameY":-2,"height":155,"name":"face1","x":875},{"frameHeight":159,"y":1,"frameWidth":126,"frameX":-2,"width":122,"frameY":-2,"height":155,"name":"face2","x":875},{"frameHeight":159,"y":315,"frameWidth":126,"frameX":-2,"width":122,"frameY":-2,"height":155,"name":"face0","x":875},{"frameHeight":158,"y":1,"frameWidth":126,"frameX":-2,"width":122,"frameY":-2,"height":154,"name":"face3","x":211},{"frameHeight":42,"y":472,"frameWidth":44,"frameX":-2,"width":40,"frameY":-2,"height":38,"name":"eye1","x":849},{"frameHeight":26,"y":472,"frameWidth":42,"frameX":-2,"width":38,"frameY":-2,"height":22,"name":"eye3","x":933},{"frameHeight":45,"y":157,"frameWidth":40,"frameX":-2,"width":36,"frameY":-2,"height":40,"name":"eye0","x":211},{"frameHeight":42,"y":472,"frameWidth":44,"frameX":-2,"width":40,"frameY":-2,"height":38,"name":"eye2","x":891},{"frameHeight":19,"y":157,"frameWidth":19,"frameX":-2,"width":15,"frameY":-2,"height":15,"name":"eyeHeart_red","x":282},{"frameHeight":17,"y":157,"frameWidth":17,"frameX":-2,"width":13,"frameY":-2,"height":13,"name":"eyeHeart","x":319},{"frameHeight":14,"y":157,"frameWidth":22,"frameX":-2,"width":18,"frameY":-2,"height":10,"name":"eyebrowL","x":299},{"frameHeight":14,"y":498,"frameWidth":22,"frameX":-2,"width":18,"frameY":-2,"height":10,"name":"eyebrowR","x":993},{"frameHeight":37,"y":472,"frameWidth":22,"frameX":-2,"width":18,"frameY":-2,"height":33,"name":"mouth_wide","x":973},{"frameHeight":22,"y":157,"frameWidth":35,"frameX":-2,"width":31,"frameY":-2,"height":18,"name":"mouth_bite","x":249},{"frameHeight":28,"y":472,"frameWidth":28,"frameX":-2,"width":24,"frameY":-2,"height":24,"name":"mouth_open","x":993},{"frameHeight":25,"y":375,"frameWidth":28,"frameX":-2,"width":24,"frameY":-2,"height":21,"name":"mouth","x":849},{"frameHeight":118,"y":259,"frameWidth":194,"frameX":-2,"width":190,"frameY":-2,"height":114,"name":"cos_fire","x":683},{"frameHeight":19,"y":496,"frameWidth":31,"frameX":-2,"width":26,"frameY":-2,"height":15,"name":"eyeCover","x":933},{"frameHeight":272,"y":1,"frameWidth":229,"frameX":-10,"width":208,"frameY":-10,"height":256,"name":"food_light_outer","x":1},{"frameHeight":237,"y":259,"frameWidth":192,"frameX":-6,"width":180,"frameY":-6,"height":225,"name":"food_light_inner","x":1},{"frameHeight":195,"y":259,"frameWidth":183,"frameX":-8,"width":165,"frameY":-11,"height":173,"name":"food_lightning","x":349},{"frameHeight":213,"y":259,"frameWidth":168,"frameX":-2,"width":164,"frameY":-2,"height":209,"name":"armor0","x":183},{"frameHeight":26,"y":398,"frameWidth":27,"frameX":-2,"width":22,"frameY":-2,"height":22,"name":"armor_green","x":849},{"frameHeight":128,"y":375,"frameWidth":168,"frameX":-2,"width":164,"frameY":-2,"height":123,"name":"armor1","x":683},{"frameHeight":26,"y":446,"frameWidth":27,"frameX":-2,"width":22,"frameY":-2,"height":22,"name":"armor_yellow","x":849},{"frameHeight":62,"y":430,"frameWidth":159,"frameX":-2,"width":155,"frameY":-1,"height":59,"name":"armor2","x":516},{"frameHeight":26,"y":422,"frameWidth":27,"frameX":-2,"width":22,"frameY":-2,"height":22,"name":"armor_red","x":849},{"frameHeight":181,"y":259,"frameWidth":178,"frameX":-3,"width":165,"frameY":-3,"height":169,"name":"blink","x":516}]}]],0,0,[0],[5],[2]]]]
